mysql2mongodb/__init__.py
mysql2mongodb/database/__init__.py
mysql2mongodb/database/mongodb/__init__.py
mysql2mongodb/database/mysql/__init__.py
mysql2mongodb/logging/__init__.py
mysql2mongodb/shell/__init__.py
mysql2mongodb-0.0.1.data/scripts/mysql2mongo.py
mysql2mongodb-0.0.1.data/scripts/mysql2mongoDB
mysql2mongodb-0.0.1.dist-info/LICENSE
mysql2mongodb-0.0.1.dist-info/METADATA
mysql2mongodb-0.0.1.dist-info/WHEEL
mysql2mongodb-0.0.1.dist-info/top_level.txt
mysql2mongodb-0.0.1.dist-info/RECORD
